asyncgui_ext/queue.py
asyncgui_ext_queue-0.3.1.dist-info/LICENSE
asyncgui_ext_queue-0.3.1.dist-info/METADATA
asyncgui_ext_queue-0.3.1.dist-info/WHEEL
asyncgui_ext_queue-0.3.1.dist-info/RECORD
