Metadata-Version: 2.3
Name: asyncgui-ext-queue
Version: 0.3.1
Summary: An asyncio.Queue equivalence for asyncgui
License: MIT
Keywords: async
Author: Nattōsai Mitō
Author-email: flow4re2c@gmail.com
Requires-Python: >=3.10,<4.0
Classifier: Development Status :: 5 - Production/Stable
Classifier: Intended Audience :: Developers
Classifier: License :: OSI Approved :: MIT License
Classifier: Operating System :: OS Independent
Classifier: Programming Language :: Python
Classifier: Programming Language :: Python :: 3
Classifier: Programming Language :: Python :: 3.10
Classifier: Programming Language :: Python :: 3.11
Classifier: Programming Language :: Python :: 3.12
Classifier: Programming Language :: Python :: 3.13
Classifier: Topic :: Software Development :: Libraries
Requires-Dist: asyncgui (>=0.9.3,<1.0.0)
Project-URL: Homepage, https://github.com/asyncgui/asyncgui-ext-queue
Project-URL: Repository, https://github.com/asyncgui/asyncgui-ext-queue
